pydonodoo/__init__.py
pydonodoo/donodoo.py
python_donodoo-0.1.0.dist-info/METADATA
python_donodoo-0.1.0.dist-info/WHEEL
python_donodoo-0.1.0.dist-info/top_level.txt
python_donodoo-0.1.0.dist-info/RECORD
